mikelint/__init__.py
mikelint/__main__.py
mikelint/config.yaml
mikelint/run.py
mikelint/type_hints.py
mikelint/analysers/__init__.py
mikelint/analysers/analyser.py
mikelint/analysers/class_instance.py
mikelint/analysers/docstrings.py
mikelint/analysers/encapsulation.py
mikelint/analysers/naming.py
mikelint/analysers/scope.py
mikelint/analysers/structure.py
mikelint/formatters/__init__.py
mikelint/formatters/base_formatter.py
mikelint/formatters/formatter_.py
mikelint/formatters/json_formatter.py
mikelint/utils/__init__.py
mikelint/utils/encoders.py
mikelint/utils/strings.py
mikelint/utils/tree.py
mikelint/utils/violation.py
mikelint-1.2.6.dist-info/LICENSE
mikelint-1.2.6.dist-info/METADATA
mikelint-1.2.6.dist-info/WHEEL
mikelint-1.2.6.dist-info/top_level.txt
mikelint-1.2.6.dist-info/RECORD
