Metadata-Version: 2.1
Name: mikelint
Version: 1.2.6
Summary: Linter used for CSSE1001 at UQ
Home-page: https://github.com/mike-fam/mikelint
Author: Mike Pham
Author-email: mikepham1207@gmail.com
License: MIT
Classifier: License :: OSI Approved :: MIT License
Classifier: Programming Language :: Python :: 3.9
Requires-Python: >=3.8
License-File: LICENSE
Requires-Dist: astroid <3.0.0,>=2.5.6
Requires-Dist: PyYAML ==5.3.1
